darklight/__init__.py
darklight/datasets/__init__.py
darklight/datasets/classes.py
darklight/datasets/dataset.py
darklight/losses/__init__.py
darklight/losses/losses.py
darklight/models/__init__.py
darklight/trainer/__init__.py
darklight/trainer/timer.py
darklight/trainer/trainer.py
darklight/trtengine/__init__.py
darklight/trtengine/clsengine.py
darklight/trtengine/trtengine.py
darklight/utils/__init__.py
darklight/utils/exportonnx.py
darklight-0.4.dist-info/LICENSE
darklight-0.4.dist-info/METADATA
darklight-0.4.dist-info/WHEEL
darklight-0.4.dist-info/top_level.txt
darklight-0.4.dist-info/RECORD
