Metadata-Version: 2.1
Name: darklight
Version: 0.4
Summary: A library for accelerating knowledge distillation training
Home-page: https://github.com/dataplayer12/darklight
Author: Jaiyam Sharma
Author-email: jaiyamsharma@gmail.com
Classifier: Development Status :: 4 - Beta
Classifier: Intended Audience :: Developers
Classifier: Programming Language :: Python :: 3
Classifier: Topic :: Scientific/Engineering :: Artificial Intelligence
Classifier: License :: OSI Approved :: MIT License
License-File: LICENSE
Requires-Dist: numpy
Requires-Dist: torch
Requires-Dist: pycuda
